{
  "title": "Built-in string subtype",
  "description": "This BBE demonstrates the built-in string subtype string:Char in Ballerina.",
  "keywords": [
    "ballerina",
    "ballerina by example",
    "bbe",
    "string",
    "string subtype",
    "Char"
  ],
  "permalink": "/learn/by-example/built-in-string-subtype",
  "active": "built-in-string-subtype",
  "redirect_from": [
    "/swan-lake/learn/by-example/built-in-string-subtype",
    "/swan-lake/learn/by-example/built-in-string-subtype.html"
  ]
}
