{
  "modules": [
    {
      "id": "reflect",
      "description": "",
      "orgName": "ballerina",
      "version": "0.6.0-alpha4"
    }
  ],
  "classes": [],
  "functions": [
    {
      "id": "getResourceAnnotations",
      "description": "Function to retrieve the resource\u0027s annotation.",
      "moduleId": "reflect",
      "moduleOrgName": "ballerina",
      "moduleVersion": "0.6.0-alpha4"
    },
    {
      "id": "getServiceAnnotations",
      "description": "Function to retrieve the service\u0027s annotation.",
      "moduleId": "reflect",
      "moduleOrgName": "ballerina",
      "moduleVersion": "0.6.0-alpha4"
    }
  ],
  "records": [],
  "constants": [],
  "errors": [],
  "types": [],
  "clients": [],
  "listeners": [],
  "annotations": [],
  "abstractObjects": [],
  "enums": []
}